tpltable/__init__.py
tpltable/basic.py
tpltable/core.py
tpltable/earray.py
tpltable/excel.py
tpltable/main.py
tpltable/style.py
tpltable/style_demo.py
tpltable/table.py
tpltable-0.3.6.dist-info/METADATA
tpltable-0.3.6.dist-info/WHEEL
tpltable-0.3.6.dist-info/top_level.txt
tpltable-0.3.6.dist-info/RECORD
