Metadata-Version: 2.4
Name: tpltable
Version: 0.3.6
Summary: define "Excel" "Table|StyleTable" "Row|Col|StyleRow|StyleCol". Can dynamic modify excel data & styles. Support multiple kinds of indexes. (70%)
Author-email: 2229066748@qq.com
Maintainer: Eagle'sBaby
Maintainer-email: 2229066748@qq.com
License: Apache Licence 2.0
Keywords: excel,auto,copy
Classifier: Programming Language :: Python
Classifier: Programming Language :: Python :: 3
Requires-Python: >=3
Requires-Dist: openpyxl
Requires-Dist: numpy
Requires-Dist: files3
Dynamic: author-email
Dynamic: classifier
Dynamic: keywords
Dynamic: license
Dynamic: maintainer
Dynamic: maintainer-email
Dynamic: requires-dist
Dynamic: requires-python
Dynamic: summary
